{
  "ActionRequiredByDateTime": null,
  "Attachments": null,
  "AttachmentsArchive": null,
  "Body": {
    "Content": "We are announcing the ability to re-enable locked customer managed key environments in  \n\nPower Platform admin center. This public preview feature will begin rolling out globally on July 23, 2025, with an anticipated rollout completion of July 30, 2025.<br><br><b>How does this affect me?</b><br>Previously, if customer-managed key environments were deactivated due to the revocation of key access of the enterprise policy, you needed to submit a support ticket to activate these environments once the key access was restored.<br><br>Now, administrators can unlock and activate environments directly through the Power Platform admin center. They can also identify which environments were deactivated due to unhealthy enterprise policies and proactively manage these environments to ensure smooth operations.<br><br><b>What action do I need to take?</b><br>This message is for awareness and no action is required.<br><br>If you would like more information on this feature, please visit <a target=\"_blank\" href=\"https://aka.ms/ADO11590\">Lock and unlock environments through key vaults access – Power Platform</a>.",
    "ContentType": "html"
  },
  "Category": "stayInformed",
  "Details": [],
  "EndDateTime": "2025-08-23T21:07:54Z",
  "HasAttachments": false,
  "Id": "MC1120631",
  "IsMajorChange": false,
  "LastModifiedDateTime": "2025-07-23T21:09:41.747Z",
  "Services": [
    "Power Platform"
  ],
  "Severity": "normal",
  "StartDateTime": "2025-07-23T21:07:54Z",
  "Tags": [
    "New feature"
  ],
  "Title": "Power Platform admin center - Unlock customer managed key environments by restoring access to the key vault",
  "ViewPoint": {
    "IsArchived": null,
    "IsFavorited": null,
    "IsRead": null
  },
  "AdditionalProperties": {}
}
