{
  "IsMajorChange": false,
  "Type": "roadmap",
  "PubDate": "Tue, 21 Mar 2023 23:23:13 Z",
  "Services": "M",
  "Categories": [
    "Rolling out",
    "General Availability",
    "Targeted Release (Entire Organization)",
    "Targeted Release (Select People)",
    "Worldwide (Standard Multi-Tenant)",
    "GCC",
    "GCC High",
    "DoD",
    "Microsoft Teams",
    "Desktop",
    "Mac"
  ],
  "LastModifiedDateTime": "Tue, 21 Mar 2023 23:23:13 Z",
  "Title": "Microsoft Teams: Ability for meeting participants to edit their display name",
  "Id": "122934",
  "Link": "https://www.microsoft.com/microsoft-365/roadmap?id=122934",
  "Description": "<div>Teams meeting participants will be able to edit their display name, enabling more flexibility in their meeting presence, regardless of their tenant set display name. Users can make this change during the meeting and it will persist throughout the duration of the meeting. </div><br>GA date: March CY2025"
}
