{
  "Services": "Microsoft 365 Apps",
  "PubDate": "Mon, 22 Apr 2024 23:15:43 Z",
  "Id": "366127",
  "LastModifiedDateTime": "Mon, 22 Apr 2024 23:15:43 Z",
  "Link": "https://www.microsoft.com/microsoft-365/roadmap?id=366127",
  "IsMajorChange": false,
  "Categories": [
    "Launched",
    "General Availability",
    "Worldwide (Standard Multi-Tenant)",
    "Excel",
    "Web"
  ],
  "Type": "roadmap",
  "Title": "Excel: Comment filtering",
  "Description": "Enable filtering capabilities for the comment pane.<br>GA date: April CY2024"
}
