{
  "Description": "Solution displays M365 header in Viva Glint to improve discoverability of other M365 apps <br>GA date: August CY2024",
  "IsMajorChange": false,
  "Title": "Microsoft Viva: Viva Glint - Access to M365 header",
  "PubDate": "Wed, 21 Feb 2024 00:00:00 Z",
  "Categories": [
    "Launched",
    "General Availability",
    "Worldwide (Standard Multi-Tenant)",
    "Microsoft Viva",
    "Web"
  ],
  "Id": "383724",
  "Link": "https://www.microsoft.com/microsoft-365/roadmap?id=383724",
  "LastModifiedDateTime": "Wed, 21 Feb 2024 00:00:00 Z",
  "Type": "roadmap",
  "Services": "Microsoft Viva"
}
