{
  "PubDate": "Thu, 14 Mar 2024 00:15:09 Z",
  "Title": "Microsoft Viva: Dashboard personalization on tablet in Viva Connections",
  "Description": "Customize your dashboard by adding, removing, or reordering the dashboard cards.<br>GA date: June CY2024",
  "Id": "388368",
  "LastModifiedDateTime": "Thu, 14 Mar 2024 00:15:09 Z",
  "Link": "https://www.microsoft.com/microsoft-365/roadmap?id=388368",
  "Services": "Microsoft Viva",
  "Categories": [
    "Launched",
    "General Availability",
    "Worldwide (Standard Multi-Tenant)",
    "Microsoft Viva",
    "Android",
    "iOS"
  ],
  "IsMajorChange": false,
  "Type": "roadmap"
}
