{
  "Id": "412937",
  "IsMajorChange": false,
  "Services": "Outlook",
  "LastModifiedDateTime": "Wed, 21 Aug 2024 23:45:23 Z",
  "Title": "Outlook: Copy list of attendees to clipboard",
  "PubDate": "Wed, 21 Aug 2024 23:45:23 Z",
  "Description": "Allow users to copy the list of attendees to clipboard from calendar event. #newoutlookforwindows<br>GA date: October CY2024",
  "Type": "roadmap",
  "Link": "https://www.microsoft.com/microsoft-365/roadmap?id=412937",
  "Categories": [
    "Launched",
    "General Availability",
    "Targeted Release",
    "Worldwide (Standard Multi-Tenant)",
    "Outlook",
    "Desktop",
    "Web"
  ]
}
