{
  "IsMajorChange": false,
  "Type": "roadmap",
  "PubDate": "Thu, 12 Sep 2024 00:00:50 Z",
  "Services": "M",
  "Categories": [
    "Launched",
    "General Availability",
    "GCC High",
    "Microsoft Project",
    "Web"
  ],
  "LastModifiedDateTime": "Thu, 12 Sep 2024 00:00:50 Z",
  "Title": "Microsoft Project: Project for the web and Roadmap for GCCH",
  "Id": "416299",
  "Link": "https://www.microsoft.com/microsoft-365/roadmap?id=416299",
  "Description": "Project for the web and Roadmap features are rolling out to Project GGCH customers.<br>GA date: October CY2024"
}
