{
  "Id": "419814",
  "IsMajorChange": false,
  "Services": [
    "OneDrive for Business",
    "SharePoint Online"
  ],
  "LastModifiedDateTime": "Thu, 03 Oct 2024 23:30:37 Z",
  "Title": "OneDrive: Hide people previewing files in OneDrive and SharePoint",
  "PubDate": "Thu, 03 Oct 2024 23:30:37 Z",
  "Description": "This setting will allow administrators to disable the presence feature in the OneDrive and SharePoint file previewing experience on selected sites. This item is inaccurate and is being removed from the roadmap.  We apologize for any inconvenience.<br>GA date: October CY2024",
  "Type": "roadmap",
  "Link": "https://www.microsoft.com/microsoft-365/roadmap?id=419814",
  "Categories": [
    "Launched",
    "General Availability",
    "Worldwide (Standard Multi-Tenant)",
    "GCC",
    "GCC High",
    "DoD",
    "OneDrive",
    "SharePoint",
    "Web"
  ]
}
