{
  "Description": "Currently, leaders are managed in Viva Engage manually. If you wish to add or remove leaders, you need to go to Engage to do so. This feature will allow you to define a group that includes users who should be designated as leaders. As you add or remove people from that group, they will gain or lose privileges accordingly. The manual method will continue to be available.<br>GA date: May CY2025",
  "IsMajorChange": false,
  "Title": "Microsoft Viva: Viva Engage - Leaders updated via group sync",
  "PubDate": "Wed, 09 Oct 2024 23:15:44 Z",
  "Categories": [
    "In development",
    "General Availability",
    "Worldwide (Standard Multi-Tenant)",
    "Microsoft Viva",
    "Web"
  ],
  "Id": "420946",
  "Link": "https://www.microsoft.com/microsoft-365/roadmap?id=420946",
  "LastModifiedDateTime": "Wed, 09 Oct 2024 23:15:44 Z",
  "Type": "roadmap",
  "Services": "Microsoft Viva"
}
