{
  "IsMajorChange": false,
  "Type": "roadmap",
  "PubDate": "Thu, 17 Oct 2024 23:15:03 Z",
  "Services": "Microsoft Copilot (Microsoft 365)",
  "Categories": [
    "Launched",
    "General Availability",
    "Worldwide (Standard Multi-Tenant)",
    "Microsoft Copilot (Microsoft 365)",
    "Web"
  ],
  "LastModifiedDateTime": "Thu, 17 Oct 2024 23:15:03 Z",
  "Title": "Microsoft Copilot (Microsoft 365): BizChat - Copilot agents available in Business Chat web mode",
  "Id": "422315",
  "Link": "https://www.microsoft.com/microsoft-365/roadmap?id=422315",
  "Description": "In Business Chat web mode, discover and use Copilot agents available for your organization. Agents are custom grounded chats that include specific knowledge sources from work and web.<br>GA date: January CY2025<br>Preview date: November CY2024"
}
