{
  "Services": "Microsoft Teams",
  "PubDate": "Wed, 27 Nov 2024 00:00:04 Z",
  "Id": "469496",
  "LastModifiedDateTime": "Wed, 27 Nov 2024 00:00:04 Z",
  "Link": "https://www.microsoft.com/microsoft-365/roadmap?id=469496",
  "IsMajorChange": false,
  "Categories": [
    "Launched",
    "General Availability",
    "Targeted Release",
    "Worldwide (Standard Multi-Tenant)",
    "Microsoft Teams",
    "Desktop"
  ],
  "Type": "roadmap",
  "Title": "Microsoft Teams: Auto detection of room audio in BYOD rooms expanded to audio devices with video",
  "Description": "The room audio auto-detect and pre-select feature for BYOD rooms that was released in October 2024 now activates the video component of composite audio-video peripherals as the selected camera in Teams.<br>GA date: May CY2025"
}
