{
  "IsMajorChange": false,
  "Type": "roadmap",
  "PubDate": "Wed, 19 Feb 2025 00:00:11 Z",
  "Services": "M",
  "Categories": [
    "Launched",
    "General Availability",
    "Worldwide (Standard Multi-Tenant)",
    "Microsoft Viva",
    "Web"
  ],
  "LastModifiedDateTime": "Wed, 19 Feb 2025 00:00:11 Z",
  "Title": "Microsoft Viva: Viva Glint - Enhance the Comment Experience for Live Surveys",
  "Id": "478914",
  "Link": "https://www.microsoft.com/microsoft-365/roadmap?id=478914",
  "Description": "Updating the survey experience to provide ability to display the comment box on the screen when a user is providing a rating. Currently, the survey automatically progresses to the next question after the user selects a rating, without giving them an opportunity to leave a comment. With this change, the program will have the ability for the comment box will be persistently visible, encouraging users to provide more qualitative feedback alongside their rating.<br>GA date: March CY2025"
}
