{
  "Link": "https://www.microsoft.com/microsoft-365/roadmap?id=478926",
  "Description": "Remove the 22-inch size limit and modernize Access forms and reports work well on large format monitors and provide responsive behavior for different form factors.<br>GA date: September CY2025",
  "LastModifiedDateTime": "Thu, 03 Apr 2025 23:45:17 Z",
  "Id": "478926",
  "Categories": [
    "In development",
    "General Availability",
    "Worldwide (Standard Multi-Tenant)",
    "Access",
    "Desktop"
  ],
  "PubDate": "Thu, 03 Apr 2025 23:45:17 Z",
  "Services": "Access",
  "Title": "Access: Modernize Access Forms and Reports to work well on Large Format Monitors",
  "IsMajorChange": false,
  "Type": "roadmap"
}
