{
  "IsMajorChange": false,
  "Type": "roadmap",
  "PubDate": "Wed, 05 Feb 2025 00:15:53 Z",
  "Services": "Microsoft Viva",
  "Categories": [
    "Launched",
    "General Availability",
    "Preview",
    "Worldwide (Standard Multi-Tenant)",
    "Microsoft Viva",
    "Desktop",
    "Web"
  ],
  "LastModifiedDateTime": "Wed, 05 Feb 2025 00:15:53 Z",
  "Title": "Microsoft Viva: Viva Learning - Semantic search support for in-app Searches",
  "Id": "479749",
  "Link": "https://www.microsoft.com/microsoft-365/roadmap?id=479749",
  "Description": "Semantic search capability understands context and nuances of user queries, providing more accurate and relevant results.<br>GA date: March CY2025<br>Preview date: February CY2025"
}
