{
  "Categories": [
    "Launched",
    "General Availability",
    "GCC",
    "GCC High",
    "DoD",
    "Outlook",
    "Web"
  ],
  "Id": "481355",
  "IsMajorChange": false,
  "Description": "Get assistance with time suggestions when creating new meetings in modern Outlook. This feature is currently supported for non-recurring meetings only. #newoutlookforwindows<br>GA date: March CY2025",
  "PubDate": "Wed, 19 Feb 2025 00:00:11 Z",
  "Title": "Outlook: Time Suggestions assistance while creating new meetings",
  "Link": "https://www.microsoft.com/microsoft-365/roadmap?id=481355",
  "Type": "roadmap",
  "Services": "Outlook",
  "LastModifiedDateTime": "Wed, 19 Feb 2025 00:00:11 Z"
}
