{
  "Title": "Outlook: Create and save email templates in the new Outlook for Windows",
  "Type": "roadmap",
  "LastModifiedDateTime": "Tue, 18 Mar 2025 23:15:13 Z",
  "Services": "Outlook",
  "Id": "485757",
  "IsMajorChange": false,
  "PubDate": "Tue, 18 Mar 2025 23:15:13 Z",
  "Categories": [
    "In development",
    "General Availability",
    "Worldwide (Standard Multi-Tenant)",
    "GCC",
    "GCC High",
    "DoD",
    "Outlook",
    "Desktop"
  ],
  "Link": "https://www.microsoft.com/microsoft-365/roadmap?id=485757",
  "Description": "The template feature in the new Outlook allows users to create and save email templates for quick and consistent communication, streamlining the process of sending repetitive messages. Additionally, it allows for the seamless import of templates saved as .oft files. #newoutlookforwindows<br>GA date: September CY2025"
}
