{
  "IsMajorChange": false,
  "Type": "roadmap",
  "PubDate": "Fri, 18 Apr 2025 22:15:14 Z",
  "Services": "S",
  "Categories": [
    "In development",
    "General Availability",
    "Targeted Release",
    "Worldwide (Standard Multi-Tenant)",
    "GCC",
    "GCC High",
    "DoD",
    "SharePoint",
    "Web"
  ],
  "LastModifiedDateTime": "Fri, 18 Apr 2025 22:15:14 Z",
  "Title": "SharePoint: Copilot actions in SharePoint document libraries",
  "Id": "488297",
  "Link": "https://www.microsoft.com/microsoft-365/roadmap?id=488297",
  "Description": "When you select an item in OneDrive on the Web, the Copilot button appears, offering a range of actions you can perform on that item. The same feature and actions are coming to document library views in SharePoint and Teams.<br>GA date: May CY2025"
}
