{
  "Description": "Within Microsoft Purview Data Security Posture Management for AI, a specific page is dedicated to showing protection capabilities and usage for M365 Copilot.<br>GA date: July CY2025<br>Preview date: June CY2025",
  "IsMajorChange": false,
  "Title": "Microsoft Purview Compliance Portal: Data Security Posture Management for AI - M365 Copilot view",
  "PubDate": "Mon, 14 Apr 2025 23:15:33 Z",
  "Categories": [
    "In development",
    "General Availability",
    "Preview",
    "Worldwide (Standard Multi-Tenant)",
    "Microsoft Purview compliance portal",
    "Microsoft Copilot (Microsoft 365)",
    "Web"
  ],
  "Id": "489828",
  "Link": "https://www.microsoft.com/microsoft-365/roadmap?id=489828",
  "LastModifiedDateTime": "Mon, 14 Apr 2025 23:15:33 Z",
  "Type": "roadmap",
  "Services": [
    "Microsoft Copilot (Microsoft 365)",
    "Microsoft Purview compliance portal"
  ]
}
