{
  "Type": "roadmap",
  "PubDate": "Wed, 23 Apr 2025 16:15:28 Z",
  "Categories": [
    "Launched",
    "General Availability",
    "Worldwide (Standard Multi-Tenant)",
    "Microsoft Copilot (Microsoft 365)",
    "OneNote",
    "Web"
  ],
  "Description": "M365 Copilot experiences can now reason over your OneNote content<br>GA date: May CY2025",
  "Title": "Microsoft Copilot (Microsoft 365): OneNote Pages in M365 Copilot",
  "Id": "490722",
  "Link": "https://www.microsoft.com/microsoft-365/roadmap?id=490722",
  "Services": [
    "Microsoft Copilot (Microsoft 365)",
    "OneNote"
  ],
  "LastModifiedDateTime": "Wed, 23 Apr 2025 16:15:28 Z",
  "IsMajorChange": false
}
