{
  "Description": "Teams Administrators will have the ability to remotely collect client diagnostics logs for troubleshooting from users' devices, aiming to minimize or eliminate the need for user intervention and workflow disruption previously required for collecting diagnostics logs.<br>GA date: July CY2025",
  "IsMajorChange": false,
  "Title": "Microsoft Teams: Remote log collection in Teams admin center​",
  "PubDate": "Tue, 29 Apr 2025 23:15:05 Z",
  "Categories": [
    "In development",
    "General Availability",
    "Targeted Release",
    "Worldwide (Standard Multi-Tenant)",
    "Microsoft Teams",
    "Desktop",
    "Mac"
  ],
  "Id": "491439",
  "Link": "https://www.microsoft.com/microsoft-365/roadmap?id=491439",
  "LastModifiedDateTime": "Tue, 29 Apr 2025 23:15:05 Z",
  "Type": "roadmap",
  "Services": "Microsoft Teams"
}
