{
  "LastModifiedDateTime": "Thu, 15 May 2025 23:15:36 Z",
  "Link": "https://www.microsoft.com/microsoft-365/roadmap?id=494153",
  "Id": "494153",
  "Services": "Outlook",
  "Categories": [
    "In development",
    "Current Channel",
    "General Availability",
    "Worldwide (Standard Multi-Tenant)",
    "GCC",
    "Outlook",
    "Desktop"
  ],
  "Description": "We're introducing a sidebar experience for Copilot Chat in classic Outlook for Windows. Now, you'll be able to chat with Copilot alongside and in the context of the content you're reading or writing in Outlook. <br>GA date: July CY2025",
  "PubDate": "Thu, 15 May 2025 23:15:36 Z",
  "Title": "Outlook: Copilot chat in a sidebar in classic Outlook for Windows",
  "Type": "roadmap",
  "IsMajorChange": false
}
