{
  "Services": "Microsoft Intune",
  "Type": "roadmap",
  "LastModifiedDateTime": "Fri, 25 Jul 2025 22:15:54 Z",
  "Link": "https://www.microsoft.com/microsoft-365/roadmap?id=499155",
  "Id": "499155",
  "IsMajorChange": false,
  "Title": "Microsoft Intune: Intune Suite - Endpoint Privilege Management Virtual Account Support",
  "Categories": [
    "In development",
    "General Availability",
    "Worldwide (Standard Multi-Tenant)",
    "GCC",
    "GCC High",
    "DoD",
    "Microsoft Intune",
    "Desktop"
  ],
  "Description": "EPM will introduce a per-rule option to run elevated apps with the original user's identity context, preserving app data, save locations, and preferences. This offers a more personalized app runtime experience compared to the default virtual account.<br>GA date: October CY2025",
  "PubDate": "Fri, 25 Jul 2025 22:15:54 Z"
}
