{
  "Link": "https://www.microsoft.com/microsoft-365/roadmap?id=500634",
  "IsMajorChange": false,
  "Description": "We are bringing Pages to your Teams Channel experience. Create and collaborate using Pages directly in any of your channels.<br>GA date: October CY2025",
  "PubDate": "Thu, 14 Aug 2025 23:15:02 Z",
  "Type": "roadmap",
  "Categories": [
    "In development",
    "General Availability",
    "Worldwide (Standard Multi-Tenant)",
    "Microsoft Teams",
    "Desktop"
  ],
  "LastModifiedDateTime": "Thu, 14 Aug 2025 23:15:02 Z",
  "Id": "500634",
  "Services": "Microsoft Teams",
  "Title": "Microsoft Teams: Collaborate using Pages in Channels"
}
