{
  "LastModifiedDateTime": "Tue, 19 Aug 2025 23:15:40 Z",
  "Description": "We are expanding the access to Diagnostics beyond Global Admin to: Compliance Administrator, Security Administrator and Organization Management.<br>GA date: December CY2025<br>Preview date: September CY2025",
  "Title": "Microsoft Purview compliance portal: Data Loss Prevention - Expanding access to Diagnostics to Compliance Administrator, Security Administrator and Organization Management",
  "IsMajorChange": false,
  "Link": "https://www.microsoft.com/microsoft-365/roadmap?id=500894",
  "PubDate": "Tue, 19 Aug 2025 23:15:40 Z",
  "Categories": [
    "In development",
    "General Availability",
    "Preview",
    "Worldwide (Standard Multi-Tenant)",
    "Microsoft Purview compliance portal",
    "Web"
  ],
  "Services": "Microsoft Purview compliance portal",
  "Type": "roadmap",
  "Id": "500894"
}
