{
  "LastModifiedDateTime": "Tue, 23 Sep 2025 23:15:02 Z",
  "Type": "roadmap",
  "Categories": [
    "In development",
    "General Availability",
    "Worldwide (Standard Multi-Tenant)",
    "Microsoft Teams",
    "Desktop"
  ],
  "Id": "503299",
  "IsMajorChange": false,
  "Link": "https://www.microsoft.com/microsoft-365/roadmap?id=503299",
  "Description": "The enhanced “Manage what attendees see” experience enables organizers to take their Town hall presentations to the next level. Organizers and presenters can apply layouts, backgrounds, theme colors, and name tags to deliver events that are polished, professional, and highly engaging. This feature is available to organizers with a Teams Premium license.<br>GA date: October CY2025",
  "PubDate": "Tue, 23 Sep 2025 23:15:02 Z",
  "Title": "Microsoft Teams: Customize the screen in Teams Town halls through ‘Manage what attendees see’ [Teams Premium]",
  "Services": "Microsoft Teams"
}
