{
  "Services": "Microsoft Purview compliance portal",
  "Description": "Updates to eDiscovery (Premium) review filters experience that allow admins to construct compound nested filters with either “AND” or “OR” conditions, go back and forth (undo/redo) between different iterations of filters, manage saved filter queries without navigating to a different panel, and use “Is empty/Is not empty” condition for each filter.<br>GA date: December CY2024<br>Preview date: June CY2023",
  "Link": "https://www.microsoft.com/microsoft-365/roadmap?id=124796",
  "Type": "roadmap",
  "Title": "Microsoft Purview compliance portal: eDiscovery (Premium) - Review set: Advanced filters",
  "Id": "RM124796",
  "Categories": [
    "Launched",
    "General Availability",
    "Preview",
    "Worldwide (Standard Multi-Tenant)",
    "GCC",
    "GCC High",
    "DoD",
    "Microsoft Purview compliance portal",
    "Web"
  ],
  "IsMajorChange": false,
  "LastModifiedDateTime": "Thu, 13 Apr 2023 23:11:54 Z",
  "PubDate": "Thu, 13 Apr 2023 23:11:54 Z"
}
