{
  "Title": "Microsoft Viva: Viva Goals – Improved creation, editability, and saved views in review dashboards",
  "Id": "RM165681",
  "LastModifiedDateTime": "Mon, 28 Aug 2023 23:40:43 Z",
  "Services": "Microsoft Viva",
  "Type": "roadmap",
  "PubDate": "Mon, 28 Aug 2023 23:40:43 Z",
  "IsMajorChange": false,
  "Categories": [
    "Launched",
    "General Availability",
    "Worldwide (Standard Multi-Tenant)",
    "Microsoft Viva",
    "Web"
  ],
  "Link": "https://www.microsoft.com/microsoft-365/roadmap?id=165681",
  "Description": "Users will save time in preparing for goal review\nprocesses with a simplified review dashboard creation and editing experience,\nand the ability to leverage saved views instead of starting from scratch. This item is no longer accurate and is being removed from the roadmap.  We apologize for any inconvenience. <br>GA date: December CY2023"
}
