{
  "Services": [
    "Microsoft Copilot (Microsoft 365)",
    "OneDrive for Business"
  ],
  "Description": "Copilot in OneDrive, available on OneDrive for Web, will allow you to ask questions and get information from files in your OneDrive without having to open the files. It will also summarize one or multiple files. Copilot in OneDrive will work on the following file types: DOC, DOCX, FLUID, LOOP, PPT, PPTX, XLSX, PDF, ODT, ODP, RTF, ASPX, RTF, TXT, HTM, and HTML. Copilot in OneDrive requires a Microsoft Copilot for Microsoft 365 license.<br>GA date: July CY2024",
  "Link": "https://www.microsoft.com/microsoft-365/roadmap?id=381450",
  "Type": "roadmap",
  "Title": "OneDrive: Copilot in OneDrive",
  "Id": "RM381450",
  "Categories": [
    "Launched",
    "General Availability",
    "Worldwide (Standard Multi-Tenant)",
    "Microsoft Copilot (Microsoft 365)",
    "OneDrive",
    "Web"
  ],
  "IsMajorChange": false,
  "LastModifiedDateTime": "Fri, 02 Feb 2024 00:45:19 Z",
  "PubDate": "Fri, 02 Feb 2024 00:45:19 Z"
}
