{
  "Services": "Microsoft Teams",
  "Description": "This feature allows the organizers of webinars to block the sending of attendee emails from Microsoft Teams.<br>GA date: October CY2024",
  "Link": "https://www.microsoft.com/microsoft-365/roadmap?id=392826",
  "Type": "roadmap",
  "Title": "Microsoft Teams: Ability to block Attendee Emails from Teams Webinars",
  "Id": "RM392826",
  "Categories": [
    "Launched",
    "General Availability",
    "Targeted Release",
    "Worldwide (Standard Multi-Tenant)",
    "GCC",
    "Microsoft Teams",
    "Desktop",
    "Mac"
  ],
  "IsMajorChange": false,
  "LastModifiedDateTime": "Tue, 09 Apr 2024 21:30:00 Z",
  "PubDate": "Tue, 09 Apr 2024 21:30:00 Z"
}
