{
  "Services": "Microsoft Viva",
  "Description": "These updates to Amplify Reports and Analytics provide a series of improvements to the existing experience, such as large audience scenarios to better reflect reach across the enterprise. Viva Amplify reports will now be integrated with Campaign Brief and will also include historical data. This data will be available as graphs on the reports and to download as a CSV. There will also be features for copying charts as images and downloading to PowerPoint. The historical data experience provides un...",
  "Link": "https://www.microsoft.com/microsoft-365/roadmap?id=407862",
  "Type": "roadmap",
  "Title": "Microsoft Viva: Viva Amplify - Advanced analytics",
  "Id": "RM407862",
  "Categories": [
    "Launched",
    "General Availability",
    "Worldwide (Standard Multi-Tenant)",
    "Microsoft Viva",
    "Web"
  ],
  "IsMajorChange": false,
  "LastModifiedDateTime": "Mon, 22 Jul 2024 23:30:07 Z",
  "PubDate": "Mon, 22 Jul 2024 23:30:07 Z"
}
