{
  "Title": "Microsoft Copilot (Microsoft 365): Ground prompts using SharePoint Sites",
  "Id": "RM413110",
  "LastModifiedDateTime": "Wed, 18 Sep 2024 23:15:03 Z",
  "Services": "Microsoft Copilot (Microsoft 365)",
  "Type": "roadmap",
  "PubDate": "Wed, 18 Sep 2024 23:15:03 Z",
  "IsMajorChange": false,
  "Categories": [
    "Rolling out",
    "General Availability",
    "Worldwide (Standard Multi-Tenant)",
    "Microsoft Copilot (Microsoft 365)",
    "Web"
  ],
  "Link": "https://www.microsoft.com/microsoft-365/roadmap?id=413110",
  "Description": "Users will be able to search for and select SharePoint Sites in CIQ to scope their prompts to.<br>GA date: July CY2025"
}
