{
  "Link": "https://www.microsoft.com/microsoft-365/roadmap?id=421191",
  "Id": "RM421191",
  "Categories": [
    "Launched",
    "General Availability",
    "Worldwide (Standard Multi-Tenant)",
    "Microsoft Viva",
    "Outlook",
    "Desktop",
    "Mac",
    "Web"
  ],
  "LastModifiedDateTime": "Thu, 10 Oct 2024 23:15:45 Z",
  "Services": [
    "Microsoft Viva",
    "Outlook"
  ],
  "IsMajorChange": false,
  "PubDate": "Thu, 10 Oct 2024 23:15:45 Z",
  "Title": "Outlook: Org Explorer available for all M365 commercial users",
  "Type": "roadmap",
  "Description": "Org Explorer for Outlook helps you to visualize and explore your company’s internal structure, work teams, and individual roles. This feature will be available in Outlook for all M365 enterprise users, including Microsoft Viva users.<br>GA date: May CY2025"
}
