{
  "Services": [
    "Microsoft Clipchamp",
    "Microsoft Copilot (Microsoft 365)"
  ],
  "LastModifiedDateTime": "Fri, 20 Dec 2024 00:00:02 Z",
  "IsMajorChange": false,
  "Type": "roadmap",
  "Title": "Microsoft Copilot (Microsoft 365): Clipchamp introduces Copilot-powered video creation from a prompt",
  "PubDate": "Fri, 20 Dec 2024 00:00:02 Z",
  "Link": "https://www.microsoft.com/microsoft-365/roadmap?id=471441",
  "Description": "Copilot now offers an AI-powered video creation feature in Clipchamp for work. Simply type your prompt, and Copilot will generate a bespoke script, source high-quality stock footage, and assemble a video project complete with music, voiceover, text overlays, and transitions. This provides you with a first draft, which you can edit in the Clipchamp app. You can then export the video to mp4, which will be saved in OneDrive and count towards your OneDrive quota, ready for sharing. This feature is i...",
  "Categories": [
    "Launched",
    "General Availability",
    "Preview",
    "Worldwide (Standard Multi-Tenant)",
    "Microsoft Clipchamp",
    "Microsoft Copilot (Microsoft 365)",
    "Desktop",
    "Web"
  ],
  "Id": "RM471441"
}
