{
  "Title": "Microsoft Copilot (Microsoft 365): Copilot extensibility – Developers can create, test and update custom engine agents to run in Microsoft 365 Copilot and Teams",
  "Id": "RM474439",
  "LastModifiedDateTime": "Thu, 16 Jan 2025 00:00:43 Z",
  "Services": "Microsoft Copilot (Microsoft 365)",
  "Type": "roadmap",
  "PubDate": "Thu, 16 Jan 2025 00:00:43 Z",
  "IsMajorChange": false,
  "Categories": [
    "Launched",
    "General Availability",
    "Preview",
    "Worldwide (Standard Multi-Tenant)",
    "Microsoft Copilot (Microsoft 365)",
    "Desktop",
    "Web"
  ],
  "Link": "https://www.microsoft.com/microsoft-365/roadmap?id=474439",
  "Description": "We mistakenly marked the roadmap as \"launched.\" The correct status is In Development. We apologize the inconvenience. Developers can create, test and update custom engine agents using Teams Toolkit & Microsoft Copilot Studio, so that they can run in Microsoft 365 Copilot and Teams.\n<br>GA date: June CY2025<br>Preview date: February CY2025"
}
