{
  "IsMajorChange": false,
  "PubDate": "Wed, 09 Jul 2025 23:00:43 Z",
  "Link": "https://www.microsoft.com/microsoft-365/roadmap?id=498221",
  "Description": "This feature allows Global and Intune administrators to pin the M365 Copilot app to the Windows taskbar, providing users with easy access to M365 Copilot capabilities like Chat, Search, Agents, Notebooks and Create. This setting applies to all Intune-managed Windows 10 and 11 devices with the app installed.<br>GA date: July CY2025",
  "Title": "Microsoft 365 Admin Center: Setting to pin M365 Copilot app to Windows taskbar",
  "Categories": [
    "In development",
    "General Availability",
    "Worldwide (Standard Multi-Tenant)",
    "Microsoft 365 admin center",
    "Microsoft Intune",
    "Microsoft Copilot (Microsoft 365)",
    "Web"
  ],
  "Type": "roadmap",
  "LastModifiedDateTime": "Wed, 09 Jul 2025 23:00:43 Z",
  "Services": [
    "Microsoft 365 admin center",
    "Microsoft Copilot (Microsoft 365)",
    "Microsoft Intune"
  ],
  "Id": "RM498221"
}
